asynctempfile/__init__.py
asynctempfile/temptypes.py
asynctempfile/utils.py
asynctempfile-0.5.0.dist-info/LICENSE
asynctempfile-0.5.0.dist-info/METADATA
asynctempfile-0.5.0.dist-info/WHEEL
asynctempfile-0.5.0.dist-info/top_level.txt
asynctempfile-0.5.0.dist-info/RECORD
