Metadata-Version: 2.1
Name: asynctempfile
Version: 0.5.0
Summary: Async version of tempfile
Home-page: https://github.com/alemigo/asynctempfile
Author: github.com/alemigo
License: UNKNOWN
Platform: UNKNOWN
Classifier: Programming Language :: Python :: 3
Classifier: License :: OSI Approved :: GNU General Public License v3 (GPLv3)
Classifier: Operating System :: OS Independent
Requires-Dist: aiofiles (>=0.6.0)
